sparksampling_client/__init__.py
sparksampling_client/cli.py
sparksampling_client/config.py
sparksampling_client/logging.py
sparksampling_client/session.py
sparksampling_client/proto/__init__.py
sparksampling_client/proto/sampling_service_pb2.py
sparksampling_client/proto/sampling_service_pb2_grpc.py
sparksampling_client-0.3.0.dist-info/METADATA
sparksampling_client-0.3.0.dist-info/WHEEL
sparksampling_client-0.3.0.dist-info/entry_points.txt
sparksampling_client-0.3.0.dist-info/licenses/LICENSE
sparksampling_client-0.3.0.dist-info/RECORD
