Metadata-Version: 2.1
Name: sparksampling_client
Version: 0.3.0
Summary: client for sparksampling
Project-URL: Source, https://github.com/Wh1isper/pyspark-sampling
Author-email: Wh1isper <9573586@qq.com>
License: Apache License 2.0
License-File: LICENSE
Keywords: pyspark-sampling,sparksampling_client
Classifier: Development Status :: 2 - Pre-Alpha
Classifier: Intended Audience :: Developers
Classifier: Natural Language :: English
Classifier: Programming Language :: Python :: 3
Classifier: Programming Language :: Python :: 3.5
Classifier: Programming Language :: Python :: 3.6
Classifier: Programming Language :: Python :: 3.7
Classifier: Programming Language :: Python :: 3.8
Requires-Python: >=3.7
Requires-Dist: click
Requires-Dist: sparksampling-proto==0.1.0
Provides-Extra: test
Requires-Dist: pytest; extra == 'test'
